pyMAISE/__init__.py
pyMAISE/postprocessing.py
pyMAISE/preprocessing.py
pyMAISE/settings.py
pyMAISE/tuning.py
pyMAISE/data/__init__.py
pyMAISE/data/_handler.py
pyMAISE/data/crx.csv
pyMAISE/data/fp_inp.csv
pyMAISE/data/fp_out.csv
pyMAISE/data/heat.csv
pyMAISE/data/powery.csv
pyMAISE/data/rea_inputs.csv
pyMAISE/data/rea_outputs.csv
pyMAISE/data/xs.csv
pyMAISE/methods/__init__.py
pyMAISE/methods/_dtree.py
pyMAISE/methods/_kneighbors.py
pyMAISE/methods/_lasso.py
pyMAISE/methods/_linear.py
pyMAISE/methods/_nn.py
pyMAISE/methods/_nn_wrapper.py
pyMAISE/methods/_rforest.py
pyMAISE/methods/_svr.py
pyMAISE-0.0.2.dist-info/LICENSE
pyMAISE-0.0.2.dist-info/METADATA
pyMAISE-0.0.2.dist-info/WHEEL
pyMAISE-0.0.2.dist-info/top_level.txt
pyMAISE-0.0.2.dist-info/RECORD
