Metadata-Version: 2.1
Name: pyMAISE
Version: 0.0.2
Summary: Michigan Artificial Intelligance Standard Environment
Home-page: UNKNOWN
Author: Patrick Myers
Author-email: myerspat@umich.edu
License: UNKNOWN
Platform: UNKNOWN
Requires-Dist: keras (>=2.12.0)
Requires-Dist: matplotlib
Requires-Dist: numpy
Requires-Dist: pandas
Requires-Dist: scikeras
Requires-Dist: scikit-learn
Requires-Dist: scikit-optimize
Requires-Dist: tensorflow (>=2.12.0)
Provides-Extra: stats
Requires-Dist: scipy ; extra == 'stats'
Provides-Extra: test
Requires-Dist: pytest ; extra == 'test'
